{
  "api_version": "1.0",
  "radio_banner_url": "https://res.cloudinary.com/dtauf4flo/image/upload/v1756139822/placeholder_ftffhn.png",
  "whatsapp_number": "573228745240",
  "daily_phrase": "Ser Madre, es un jerecicio constante de empatía y paciencia infinita.",
  "program_name": "Inicio de semana",
  "streaming_url": "https://stream-179.zeno.fm/nwch9v9ya0hvv?zt",
  "carousel_images": [
     {
      "id": 1,
      "url": "https://res.cloudinary.com/dtauf4flo/image/upload/v1754933169/ad_2_i6icoi.png",
       "caption": "Conoce a DJ Fénix, todos los sábados.",
      "link": "https://wa.me/573147407370"
    },
    {
      "id": 2,
      "url": "https://res.cloudinary.com/dtauf4flo/image/upload/v1754933168/ad_1_jex1is.png",
       "caption": "Conoce a DJ Fénix, todos los sábados."
    },
    {
      "id": 3,
      "url": "https://res.cloudinary.com/dtauf4flo/image/upload/v1778208889/cld-sample-2.jpg",
       "caption": "Conoce a DJ Fénix, todos los sábados."
    },
    {
      "id": 4,
      "url": "https://res.cloudinary.com/dtauf4flo/image/upload/v1778271322/entreamigas_i0zqk7.jpg",
       "caption": "Conoce a DJ Fénix, todos los sábados."
    },
    {
      "id": 5,
      "url": "https://res.cloudinary.com/dtauf4flo/image/upload/v1778430789/dia_de_la_madre_muqjpx.jpg",
       "caption": "Conoce a DJ Fénix, todos los sábados."
    },
    {
      "id": 6,
      "url": "https://res.cloudinary.com/dtauf4flo/image/upload/v1778513641/PRUEBAF1_vzu2im.jpg",
       "caption": "Conoce a DJ Fénix, todos los sábados."
    }
  ]
}
